flyshare/ApiConfig.py
flyshare/__init__.py
flyshare/__main__.py
flyshare/arp/__init__.py
flyshare/arp/account.py
flyshare/arp/portfolio.py
flyshare/arp/risk.py
flyshare/backtest/__init__.py
flyshare/backtest/analysis.py
flyshare/backtest/backtest.py
flyshare/backtest/eventengine.py
flyshare/backtest/order.py
flyshare/cmd/__init__.py
flyshare/cmd/backtest-ca&history--0.008431272646135524.csv
flyshare/cmd/backtest-pnl--0.008431272646135524.csv
flyshare/cmd/backtest_example.py
flyshare/data/DataStruct.py
flyshare/data/DataStructWarpper.py
flyshare/data/__init__.py
flyshare/data/data_fq.py
flyshare/data/data_resample.py
flyshare/data/from_DataStruct_to_proto.py
flyshare/fetch/__init__.py
flyshare/fetch/data_list.py
flyshare/fetch/query.py
flyshare/fetch/query_advance.py
flyshare/fetch/query_async.py
flyshare/fetch/tdx.py
flyshare/fetch/tdx_adv.py
flyshare/fetch/ths.py
flyshare/fetch/tushare.py
flyshare/fetch/wind.py
flyshare/language/__init__.py
flyshare/language/chinese/__init__.py
flyshare/language/chinese/constant.py
flyshare/language/chinese/text.py
flyshare/language/english/__init__.py
flyshare/language/english/constant.py
flyshare/language/english/text.py
flyshare/market/__init__.py
flyshare/market/bid.py
flyshare/market/bid_advance.py
flyshare/market/market_base.py
flyshare/market/market_config.py
flyshare/market/market_core.py
flyshare/market/market_deoc.py
flyshare/market/market_engine.py
flyshare/stock/__init__.py
flyshare/stock/fundamental.py
flyshare/stock/menu_datasource.py
flyshare/stock/trading.py
flyshare/su/__init__.py
flyshare/su/main.py
flyshare/su/save_backtest.py
flyshare/su/save_tdx.py
flyshare/su/save_tdx_file.py
flyshare/su/save_tushare.py
flyshare/su/save_wind.py
flyshare/su/update_tdx.py
flyshare/su/update_tushare.py
flyshare/su/update_wind.py
flyshare/su/user.py
flyshare/util/__init__.py
flyshare/util/bar.py
flyshare/util/conn.py
flyshare/util/csv.py
flyshare-0.0.21.dist-info/DESCRIPTION.rst
flyshare-0.0.21.dist-info/METADATA
flyshare-0.0.21.dist-info/RECORD
flyshare-0.0.21.dist-info/WHEEL
flyshare-0.0.21.dist-info/entry_points.txt
flyshare-0.0.21.dist-info/metadata.json
flyshare-0.0.21.dist-info/top_level.txt
